bronzivka/__init__.py
bronzivka/theme/bronzivka.css
bronzivka/theme/class.rst
bronzivka/theme/navbar-logo.html
bronzivka/theme/theme.conf
bronzivka-0.0.3.dist-info/METADATA
bronzivka-0.0.3.dist-info/WHEEL
bronzivka-0.0.3.dist-info/entry_points.txt
bronzivka-0.0.3.dist-info/RECORD
